docria/__init__.py
docria/algorithm.py
docria/codec.py
docria/index.py
docria/model.py
docria/printout.py
docria/query.py
docria/storage.py
docria-0.4.0.dist-info/LICENSE
docria-0.4.0.dist-info/METADATA
docria-0.4.0.dist-info/WHEEL
docria-0.4.0.dist-info/top_level.txt
docria-0.4.0.dist-info/RECORD
