Metadata-Version: 2.1
Name: docria
Version: 0.4.0
Summary: Semi-structured Document Model
Home-page: https://github.com/marcusklang/docria
Author: Marcus Klang
Author-email: marcus.klang@cs.lth.se
License: Apache 2.0
Project-URL: Source, https://github.com/marcusklang/docria
Project-URL: Tracker, https://github.com/marcusklang/docria/issues
Platform: UNKNOWN
Classifier: Development Status :: 4 - Beta
Classifier: License :: OSI Approved :: Apache Software License
Classifier: Programming Language :: Python :: 3
Classifier: Programming Language :: Python :: 3.5
Classifier: Programming Language :: Python :: 3.6
Classifier: Programming Language :: Python :: 3.7
Classifier: Intended Audience :: Developers
Classifier: Operating System :: OS Independent
Classifier: Topic :: Utilities
Requires-Dist: msgpack-python (>=0.5.6)
